donnedessousugowerner/__init__.py
donnedessousugowerner/main.py
donnedessousugowerner-0.1.1.dist-info/METADATA
donnedessousugowerner-0.1.1.dist-info/WHEEL
donnedessousugowerner-0.1.1.dist-info/RECORD
